staps/__init__.py
staps/__main__.py
staps/cli.py
staps/index.html
staps/server.py
staps-0.1.6.dist-info/DESCRIPTION.rst
staps-0.1.6.dist-info/METADATA
staps-0.1.6.dist-info/RECORD
staps-0.1.6.dist-info/WHEEL
staps-0.1.6.dist-info/entry_points.txt
staps-0.1.6.dist-info/metadata.json
staps-0.1.6.dist-info/top_level.txt
