Metadata-Version: 2.0
Name: staps
Version: 0.1.6
Summary: Simple Throw-Away Publish/Subscribe
Home-page: https://github.com/fladi/staps
Author: Michael Fladischer
Author-email: michael@openservices.at
License: BSD
Keywords: amqp,websockets,tornado,pubsub,publish,subscribe
Platform: UNKNOWN
Classifier: Development Status :: 5 - Production/Stable
Classifier: Intended Audience :: Developers
Classifier: License :: OSI Approved :: BSD License
Classifier: Operating System :: Unix
Classifier: Operating System :: POSIX
Classifier: Programming Language :: Python
Classifier: Programming Language :: Python :: 3.5
Classifier: Programming Language :: Python :: Implementation :: CPython
Classifier: Topic :: Utilities
Classifier: Topic :: Internet :: WWW/HTTP
Requires-Dist: cement
Requires-Dist: pika
Requires-Dist: tornado
